odoo10_addon_component_event-10.0.1.0.1-nspkg.pth
odoo/addons/component_event/README.rst
odoo/addons/component_event/__init__.py
odoo/addons/component_event/__manifest__.py
odoo/addons/component_event/core.py
odoo/addons/component_event/components/__init__.py
odoo/addons/component_event/components/event.py
odoo/addons/component_event/i18n/component_event.pot
odoo/addons/component_event/i18n/es.po
odoo/addons/component_event/i18n/fr.po
odoo/addons/component_event/models/__init__.py
odoo/addons/component_event/models/base.py
odoo/addons/component_event/static/description/icon.png
odoo/addons/component_event/tests/__init__.py
odoo/addons/component_event/tests/test_event.py
odoo10_addon_component_event-10.0.1.0.1.dist-info/METADATA
odoo10_addon_component_event-10.0.1.0.1.dist-info/WHEEL
odoo10_addon_component_event-10.0.1.0.1.dist-info/namespace_packages.txt
odoo10_addon_component_event-10.0.1.0.1.dist-info/top_level.txt
odoo10_addon_component_event-10.0.1.0.1.dist-info/RECORD
