Metadata-Version: 2.1
Name: odoo10-addon-component-event
Version: 10.0.1.0.1
Summary: Components Events
Home-page: https://www.camptocamp.com
Author: Camptocamp,Odoo Community Association (OCA)
Author-email: support@odoo-community.org
License: LGPL-3
Platform: UNKNOWN
Classifier: Programming Language :: Python
Classifier: Framework :: Odoo
Classifier: License :: OSI Approved :: GNU Lesser General Public License v3 (LGPLv3)
Requires-Python: ~=2.7
Requires-Dist: cachetools
Requires-Dist: odoo10-addon-component
Requires-Dist: odoo (<10.1dev,>=10.0)
